gitaddnb/__init__.py
gitaddnb/_version.py
gitaddnb/add.py
gitaddnb-0.1.0.dist-info/METADATA
gitaddnb-0.1.0.dist-info/WHEEL
gitaddnb-0.1.0.dist-info/entry_points.txt
gitaddnb-0.1.0.dist-info/top_level.txt
gitaddnb-0.1.0.dist-info/RECORD
