Metadata-Version: 2.1
Name: gitaddnb
Version: 0.1.0
Author-email: Georg Wendorf <georgwendorf@gmail.com>
Project-URL: Homepage, https://github.com/pcjedi/gitaddnb
Project-URL: Documentation, https://github.com/pcjedi/gitaddnb/blob/main/README.md
Project-URL: Repository, https://github.com/pcjedi/gitaddnb
Project-URL: Changelog, https://github.com/pcjedi/gitaddnb/releases
Project-URL: Bug Tracker, https://github.com/pcjedi/gitaddnb/issues
Requires-Python: >=3.8
